MANIFEST.in
setup.py
docs/COPYRIGHT.txt
docs/HISTORY.txt
docs/LICENSE.txt
src/dolmen/__init__.py
src/dolmen.app.site.egg-info/PKG-INFO
src/dolmen.app.site.egg-info/SOURCES.txt
src/dolmen.app.site.egg-info/dependency_links.txt
src/dolmen.app.site.egg-info/namespace_packages.txt
src/dolmen.app.site.egg-info/not-zip-safe
src/dolmen.app.site.egg-info/requires.txt
src/dolmen.app.site.egg-info/top_level.txt
src/dolmen/app/__init__.py
src/dolmen/app/site/README.txt
src/dolmen/app/site/__init__.py
src/dolmen/app/site/application.py
src/dolmen/app/site/configure.zcml
src/dolmen/app/site/ftesting.zcml
src/dolmen/app/site/tests.py