Metadata-Version: 1.0
Name: dolmen.app.site
Version: 0.2
Summary: Dolmen CMS
Home-page: http://www.dolmen-project.org
Author: Souheil Chelfouh
Author-email: trollfot@gmail.com
License: ZPL
Keywords: Grok Zope3 CMS Dolmen
Platform: Any
Classifier: Environment :: Web Environment
Classifier: Intended Audience :: Other Audience
Classifier: License :: OSI Approved :: Zope Public License
Classifier: Operating System :: OS Independent
Classifier: Programming Language :: Python
